mmogo/__init__.py
mmogo/blog/__init__.py
mmogo/company/__init__.py
mmogo/company/admin.py
mmogo/company/models.py
mmogo/core/__init__.py
mmogo/core/admin.py
mmogo/core/models.py
mmogo/core/categories/__init__.py
mmogo/core/categories/admin.py
mmogo/core/categories/models.py
mmogo/core/categories/tests.py
mmogo/core/categories/views.py
mmogo/people/__init__.py
mmogo/people/admin.py
mmogo/people/models.py
mmogocms-0.0.2.dist-info/DESCRIPTION.rst
mmogocms-0.0.2.dist-info/METADATA
mmogocms-0.0.2.dist-info/RECORD
mmogocms-0.0.2.dist-info/WHEEL
mmogocms-0.0.2.dist-info/metadata.json
mmogocms-0.0.2.dist-info/top_level.txt
