Metadata-Version: 2.0
Name: mmogocms
Version: 0.0.2
Summary: Django custom apps to help you get up and running quickly.
Home-page: http://github.com/mmogodigital/mmogocms
Author: Mmogo Digital
Author-email: dev@mmogodigital.com
License: BSD
Platform: UNKNOWN
Classifier: Programming Language :: Python
Classifier: License :: OSI Approved :: BSD License
Classifier: Development Status :: 5 - Production/Stable
Classifier: Operating System :: OS Independent
Classifier: Framework :: Django
Classifier: Intended Audience :: Developers
Classifier: Topic :: Internet :: WWW/HTTP :: Dynamic Content
Requires-Dist: Pillow
Requires-Dist: django
Requires-Dist: django-countries
Requires-Dist: django-mptt
Requires-Dist: django-taggit
